pysparkifier/__init__.py
pysparkifier/pysparkifier.py
pysparkifier/test_import.py
pysparkifier-0.8.dist-info/LICENSE
pysparkifier-0.8.dist-info/METADATA
pysparkifier-0.8.dist-info/WHEEL
pysparkifier-0.8.dist-info/top_level.txt
pysparkifier-0.8.dist-info/RECORD
